testversion/__init__.py
testversion-1.5.dist-info/METADATA
testversion-1.5.dist-info/WHEEL
testversion-1.5.dist-info/top_level.txt
testversion-1.5.dist-info/RECORD
