Metadata-Version: 2.1
Name: testversion
Version: 1.5
Summary: Testing something
Home-page: UNKNOWN
Author: Tector Pro
Author-email: UNKNOWN
License: UNKNOWN
Platform: UNKNOWN
